{"word_count": 6143, "processed_language": "en", "personality": [{"trait_id": "big5_openness", "name": "Openness", "category": "personality", "percentile": 0.9440545258186892, "raw_score": 0.7994074296533553, "children": [{"trait_id": "facet_adventurousness", "name": "Adventurousness", "category": "personality", "percentile": 0.27071818228092337, "raw_score": 0.48309943035159597}, {"trait_id": "facet_artistic_interests", "name": "Artistic interests", "category": "personality", "percentile": 0.573275097950982, "raw_score": 0.6746758205322987}, {"trait_id": "facet_emotionality", "name": "Emotionality", "category": "personality", "percentile": 0.37850289103409784, "raw_score": 0.6355805878489253}, {"trait_id": "facet_imagination", "name": "Imagination", "category": "personality", "percentile": 0.8109719343047603, "raw_score": 0.77864234595576}, {"trait_id": "facet_intellect", "name": "Intellect", "category": "personality", "percentile": 0.9979719559812228, "raw_score": 0.7402648281981252}, {"trait_id": "facet_liberalism", "name": "Authority-challenging", "category": "personality", "percentile": 0.9672812830829823, "raw_score": 0.6090174209344184}]}, {"trait_id": "big5_conscientiousness", "name": "Conscientiousness", "category": "personality", "percentile": 0.13233405465974796, "raw_score": 0.5760266071597969, "children": [{"trait_id": "facet_achievement_striving", "name": "Achievement striving", "category": "personality", "percentile": 0.39433981992544814, "raw_score": 0.6742079845269147}, {"trait_id": "facet_cautiousness", "name": "Cautiousness", "category": "personality", "percentile": 0.37603655588335333, "raw_score": 0.4725318767244809}, {"trait_id": "facet_dutifulness", "name": "Dutifulness", "category": "personality", "percentile": 0.54931350330595, "raw_score": 0.6619353207786126}, {"trait_id": "facet_orderliness", "name": "Orderliness", "category": "personality", "percentile": 0.2320992904570548, "raw_score": 0.4701803117297988}, {"trait_id": "facet_self_discipline", "name": "Self-discipline", "category": "personality", "percentile": 0.2575892815724766, "raw_score": 0.5396520126709389}, {"trait_id": "facet_self_efficacy", "name": "Self-efficacy", "category": "personality", "percentile": 0.79962295110996, "raw_score": 0.7826506927305137}]}, {"trait_id": "big5_extraversion", "name": "Extraversion", "category": "personality", "percentile": 0.9525884079426995, "raw_score": 0.6255492173266974, "children": [{"trait_id": "facet_activity_level", "name": "Activity level", "category": "personality", "percentile": 0.1278602116728833, "raw_score": 0.48222256044002765}, {"trait_id": "facet_assertiveness", "name": "Assertiveness", "category": "personality", "percentile": 0.8953266876461066, "raw_score": 0.706814743695457}, {"trait_id": "facet_cheerfulness", "name": "Cheerfulness", "category": "personality", "percentile": 0.016901426590782365, "raw_score": 0.5469118826744361}, {"trait_id": "facet_excitement_seeking", "name": "Excitement-seeking", "category": "personality", "percentile": 0.5524154219117211, "raw_score": 0.6091912278256215}, {"trait_id": "facet_friendliness", "name": "Outgoing", "category": "personality", "percentile": 0.26294546266423074, "raw_score": 0.5286754191155884}, {"trait_id": "facet_gregariousness", "name": "Gregariousness", "category": "personality", "percentile": 0.20441336250861014, "raw_score": 0.4108804265868606}]}, {"trait_id": "big5_agreeableness", "name": "Agreeableness", "category": "personality", "percentile": 0.13705028531691799, "raw_score": 0.6987201402738664, "children": [{"trait_id": "facet_altruism", "name": "Altruism", "category": "personality", "percentile": 0.531701370312483, "raw_score": 0.7078801006360944}, {"trait_id": "facet_cooperation", "name": "Cooperation", "category": "personality", "percentile": 0.056631050848436726, "raw_score": 0.48397493179620354}, {"trait_id": "facet_modesty", "name": "Modesty", "category": "personality", "percentile": 0.046541688551907046, "raw_score": 0.3597619285908662}, {"trait_id": "facet_morality", "name": "Uncompromising", "category": "personality", "percentile": 0.08276754127022046, "raw_score": 0.5603810238434833}, {"trait_id": "facet_sympathy", "name": "Sympathy", "category": "personality", "percentile": 0.9529621002077874, "raw_score": 0.7274095633375905}, {"trait_id": "facet_trust", "name": "Trust", "category": "personality", "percentile": 0.140333585090352, "raw_score": 0.5413573489874504}]}, {"trait_id": "big5_neuroticism", "name": "Emotional range", "category": "personality", "percentile": 0.55147099631619, "raw_score": 0.4746590941136599, "children": [{"trait_id": "facet_anger", "name": "Fiery", "category": "personality", "percentile": 0.8184992809765301, "raw_score": 0.5854609822313874}, {"trait_id": "facet_anxiety", "name": "Prone to worry", "category": "personality", "percentile": 0.7678809999676166, "raw_score": 0.6440243817571646}, {"trait_id": "facet_depression", "name": "Melancholy", "category": "personality", "percentile": 0.7421603636613499, "raw_score": 0.489609886816058}, {"trait_id": "facet_immoderation", "name": "Immoderation", "category": "personality", "percentile": 0.4678418363884587, "raw_score": 0.49749069336783314}, {"trait_id": "facet_self_consciousness", "name": "Self-consciousness", "category": "personality", "percentile": 0.5378850085589981, "raw_score": 0.5517190173739626}, {"trait_id": "facet_vulnerability", "name": "Susceptible to stress", "category": "personality", "percentile": 0.18252064112490163, "raw_score": 0.409912113206043}]}], "needs": [{"trait_id": "need_challenge", "name": "Challenge", "category": "needs", "percentile": 0.009944862823135614, "raw_score": 0.6273580930201825}, {"trait_id": "need_closeness", "name": "Closeness", "category": "needs", "percentile": 0.00232074575093133, "raw_score": 0.6677064912612707}, {"trait_id": "need_curiosity", "name": "Curiosity", "category": "needs", "percentile": 0.05874928620235442, "raw_score": 0.7754515007486629}, {"trait_id": "need_excitement", "name": "Excitement", "category": "needs", "percentile": 0.007432402414137451, "raw_score": 0.4917275778960776}, {"trait_id": "need_harmony", "name": "Harmony", "category": "needs", "percentile": 0.0017117609090750996, "raw_score": 0.7081912116045307}, {"trait_id": "need_ideal", "name": "Ideal", "category": "needs", "percentile": 0.01671587396972407, "raw_score": 0.5899818675308163}, {"trait_id": "need_liberty", "name": "Liberty", "category": "needs", "percentile": 0.0074636909435142895, "raw_score": 0.6453241615658301}, {"trait_id": "need_love", "name": "Love", "category": "needs", "percentile": 0.062122681191198625, "raw_score": 0.6938818649130389}, {"trait_id": "need_practicality", "name": "Practicality", "category": "needs", "percentile": 0.07695276311525306, "raw_score": 0.6969665588867686}, {"trait_id": "need_self_expression", "name": "Self-expression", "category": "needs", "percentile": 0.06520056563271837, "raw_score": 0.6228630966020826}, {"trait_id": "need_stability", "name": "Stability", "category": "needs", "percentile": 0.006112010709402205, "raw_score": 0.6546528241217251}, {"trait_id": "need_structure", "name": "Structure", "category": "needs", "percentile": 0.0024577669362455534, "raw_score": 0.619868124961444}], "values": [{"trait_id": "value_conservation", "name": "Conservation", "category": "values", "percentile": 0.0017384360057895454, "raw_score": 0.5338092886534334}, {"trait_id": "value_openness_to_change", "name": "Openness to change", "category": "values", "percentile": 0.05733995807603015, "raw_score": 0.7234376795589462}, {"trait_id": "value_hedonism", "name": "Hedonism", "category": "values", "percentile": 0.26445862962231137, "raw_score": 0.6979580843630752}, {"trait_id": "value_self_enhancement", "name": "Self-enhancement", "category": "values", "percentile": 0.048838096008852416, "raw_score": 0.633668352285228}, {"trait_id": "value_self_transcendence", "name": "Self-transcendence", "category": "values", "percentile": 0.025991960119816138, "raw_score": 0.8013073656351413}], "consumption_preferences": [{"consumption_preference_category_id": "consumption_preferences_shopping", "name": "Purchasing Preferences", "consumption_preferences": [{"consumption_preference_id": "consumption_preferences_automobile_ownership_cost", "name": "Likely to be sensitive to ownership cost when buying automobiles", "score": 1.0}, {"consumption_preference_id": "consumption_preferences_automobile_safety", "name": "Likely to prefer safety when buying automobiles", "score": 1.0}, {"consumption_preference_id": "consumption_preferences_clothes_quality", "name": "Likely to prefer quality when buying clothes", "score": 1.0}, {"consumption_preference_id": "consumption_preferences_clothes_style", "name": "Likely to prefer style when buying clothes", "score": 0.0}, {"consumption_preference_id": "consumption_preferences_clothes_comfort", "name": "Likely to prefer comfort when buying clothes", "score": 1.0}, {"consumption_preference_id": "consumption_preferences_influence_brand_name", "name": "Likely to be influenced by brand name when making product purchases", "score": 0.0}, {"consumption_preference_id": "consumption_preferences_influence_utility", "name": "Likely to be influenced by product utility when making product purchases", "score": 0.0}, {"consumption_preference_id": "consumption_preferences_influence_online_ads", "name": "Likely to be influenced by online ads when making product purchases", "score": 0.0}, {"consumption_preference_id": "consumption_preferences_influence_social_media", "name": "Likely to be influenced by social media when making product purchases", "score": 0.0}, {"consumption_preference_id": "consumption_preferences_influence_family_members", "name": "Likely to be influenced by family when making product purchases", "score": 1.0}, {"consumption_preference_id": "consumption_preferences_spur_of_moment", "name": "Likely to indulge in spur of the moment purchases", "score": 0.0}, {"consumption_preference_id": "consumption_preferences_credit_card_payment", "name": "Likely to prefer using credit cards for shopping", "score": 1.0}]}, {"consumption_preference_category_id": "consumption_preferences_health_and_activity", "name": "Health & Activity Preferences", "consumption_preferences": [{"consumption_preference_id": "consumption_preferences_eat_out", "name": "Likely to eat out frequently", "score": 0.0}, {"consumption_preference_id": "consumption_preferences_gym_membership", "name": "Likely to have a gym membership", "score": 0.0}, {"consumption_preference_id": "consumption_preferences_outdoor", "name": "Likely to like outdoor activities", "score": 1.0}]}, {"consumption_preference_category_id": "consumption_preferences_environmental_concern", "name": "Environmental Concern Preferences", "consumption_preferences": [{"consumption_preference_id": "consumption_preferences_concerned_environment", "name": "Likely to be concerned about the environment", "score": 1.0}]}, {"consumption_preference_category_id": "consumption_preferences_entrepreneurship", "name": "Entrepreneurship Preferences", "consumption_preferences": [{"consumption_preference_id": "consumption_preferences_start_business", "name": "Likely to consider starting a business in next few years", "score": 0.5}]}, {"consumption_preference_category_id": "consumption_preferences_movie", "name": "Movie Preferences", "consumption_preferences": [{"consumption_preference_id": "consumption_preferences_movie_romance", "name": "Likely to like romance movies", "score": 0.0}, {"consumption_preference_id": "consumption_preferences_movie_adventure", "name": "Likely to like adventure movies", "score": 1.0}, {"consumption_preference_id": "consumption_preferences_movie_horror", "name": "Likely to like horror movies", "score": 0.0}, {"consumption_preference_id": "consumption_preferences_movie_musical", "name": "Likely to like musical movies", "score": 1.0}, {"consumption_preference_id": "consumption_preferences_movie_historical", "name": "Likely to like historical movies", "score": 1.0}, {"consumption_preference_id": "consumption_preferences_movie_science_fiction", "name": "Likely to like science-fiction movies", "score": 1.0}, {"consumption_preference_id": "consumption_preferences_movie_war", "name": "Likely to like war movies", "score": 1.0}, {"consumption_preference_id": "consumption_preferences_movie_drama", "name": "Likely to like drama movies", "score": 1.0}, {"consumption_preference_id": "consumption_preferences_movie_action", "name": "Likely to like action movies", "score": 1.0}, {"consumption_preference_id": "consumption_preferences_movie_documentary", "name": "Likely to like documentary movies", "score": 1.0}]}, {"consumption_preference_category_id": "consumption_preferences_music", "name": "Music Preferences", "consumption_preferences": [{"consumption_preference_id": "consumption_preferences_music_rap", "name": "Likely to like rap music", "score": 0.5}, {"consumption_preference_id": "consumption_preferences_music_country", "name": "Likely to like country music", "score": 0.5}, {"consumption_preference_id": "consumption_preferences_music_r_b", "name": "Likely to like R&B music", "score": 0.5}, {"consumption_preference_id": "consumption_preferences_music_hip_hop", "name": "Likely to like hip hop music", "score": 0.0}, {"consumption_preference_id": "consumption_preferences_music_live_event", "name": "Likely to attend live musical events", "score": 1.0}, {"consumption_preference_id": "consumption_preferences_music_playing", "name": "Likely to have experience playing music", "score": 1.0}, {"consumption_preference_id": "consumption_preferences_music_latin", "name": "Likely to like Latin music", "score": 1.0}, {"consumption_preference_id": "consumption_preferences_music_rock", "name": "Likely to like rock music", "score": 1.0}, {"consumption_preference_id": "consumption_preferences_music_classical", "name": "Likely to like classical music", "score": 1.0}]}, {"consumption_preference_category_id": "consumption_preferences_reading", "name": "Reading Preferences", "consumption_preferences": [{"consumption_preference_id": "consumption_preferences_read_frequency", "name": "Likely to read often", "score": 1.0}, {"consumption_preference_id": "consumption_preferences_books_entertainment_magazines", "name": "Likely to read entertainment magazines", "score": 0.0}, {"consumption_preference_id": "consumption_preferences_books_non_fiction", "name": "Likely to read non-fiction books", "score": 1.0}, {"consumption_preference_id": "consumption_preferences_books_financial_investing", "name": "Likely to read financial investment books", "score": 1.0}, {"consumption_preference_id": "consumption_preferences_books_autobiographies", "name": "Likely to read autobiographical books", "score": 1.0}]}, {"consumption_preference_category_id": "consumption_preferences_volunteering", "name": "Volunteering Preferences", "consumption_preferences": [{"consumption_preference_id": "consumption_preferences_volunteer", "name": "Likely to volunteer for social causes", "score": 1.0}]}], "warnings": []}